{"id":"3fb554f2-962a-48f0-bda7-77d90d2c1444","revision":0,"last_node_id":383,"last_link_id":412,"nodes":[{"id":71,"type":"PreviewImage","pos":[1677.4200680650586,1545.2276911737656],"size":[291.77083333333337,457.6041666666667],"flags":{},"order":116,"mode":0,"inputs":[{"localized_name":"images","name":"images","type":"IMAGE","link":86}],"outputs":[],"properties":{"cnr_id":"comfy-core","ver":"0.11.1","Node name for S&R":"PreviewImage"},"widgets_values":[],"color":"#323","bgcolor":"#535"},{"id":73,"type":"MaskToImage","pos":[1677.4200680650586,1465.1131212316989],"size":[288.5416666666667,26],"flags":{},"order":111,"mode":0,"inputs":[{"localized_name":"mask","name":"mask","type":"MASK","link":88}],"outputs":[{"localized_name":"IMAGE","name":"IMAGE","type":"IMAGE","slot_index":0,"links":[86]}],"properties":{"cnr_id":"comfy-core","ver":"0.11.1","Node name for S&R":"MaskToImage"},"widgets_values":[],"color":"#323","bgcolor":"#535"},{"id":81,"type":"SAMModelLoader (segment anything)","pos":[1155.0226192234725,1343.4939490483482],"size":[292.70833333333337,58],"flags":{},"order":0,"mode":0,"inputs":[{"localized_name":"model_name","name":"model_name","type":"COMBO","widget":{"name":"model_name"},"link":null}],"outputs":[{"localized_name":"SAM_MODEL","name":"SAM_MODEL","type":"SAM_MODEL","links":[95]}],"properties":{"cnr_id":"comfyui_segment_anything","ver":"ab6395596399d5048639cdab7e44ec9fae857a93","Node name for S&R":"SAMModelLoader (segment anything)"},"widgets_values":["sam_vit_h (2.56GB)"]},{"id":242,"type":"GetNode","pos":[4058.257601746248,-586.3406047799411],"size":[215.1939453125,58],"flags":{},"order":1,"mode":0,"inputs":[],"outputs":[{"name":"SEEDVR2_DIT","type":"SEEDVR2_DIT","links":[265]}],"title":"Get_Upscale_DiTModel","properties":{},"widgets_values":["Upscale_DiTModel"]},{"id":243,"type":"GetNode","pos":[4054.2127065818604,-480.0159598633558],"size":[210,58],"flags":{},"order":2,"mode":0,"inputs":[],"outputs":[{"name":"SEEDVR2_VAE","type":"SEEDVR2_VAE","links":[266]}],"title":"Get_Upscale_VAEModel","properties":{},"widgets_values":["Upscale_VAEModel"]},{"id":63,"type":"SeedVR2VideoUpscaler","pos":[7021.046162840949,-738.0637827230632],"size":[269.956640625,386],"flags":{},"order":55,"mode":2,"inputs":[{"localized_name":"image","name":"image","type":"IMAGE","link":277},{"localized_name":"dit","name":"dit","type":"SEEDVR2_DIT","link":268},{"localized_name":"vae","name":"vae","type":"SEEDVR2_VAE","link":281},{"localized_name":"seed","name":"seed","type":"INT","widget":{"name":"seed"},"link":null},{"localized_name":"resolution","name":"resolution","type":"INT","widget":{"name":"resolution"},"link":null},{"localized_name":"max_resolution","name":"max_resolution","type":"INT","widget":{"name":"max_resolution"},"link":null},{"localized_name":"batch_size","name":"batch_size","type":"INT","widget":{"name":"batch_size"},"link":null},{"localized_name":"uniform_batch_size","name":"uniform_batch_size","type":"BOOLEAN","widget":{"name":"uniform_batch_size"},"link":null},{"localized_name":"color_correction","name":"color_correction","type":"COMBO","widget":{"name":"color_correction"},"link":null},{"localized_name":"temporal_overlap","name":"temporal_overlap","shape":7,"type":"INT","widget":{"name":"temporal_overlap"},"link":null},{"localized_name":"prepend_frames","name":"prepend_frames","shape":7,"type":"INT","widget":{"name":"prepend_frames"},"link":null},{"localized_name":"input_noise_scale","name":"input_noise_scale","shape":7,"type":"FLOAT","widget":{"name":"input_noise_scale"},"link":null},{"localized_name":"latent_noise_scale","name":"latent_noise_scale","shape":7,"type":"FLOAT","widget":{"name":"latent_noise_scale"},"link":null},{"localized_name":"offload_device","name":"offload_device","shape":7,"type":"COMBO","widget":{"name":"offload_device"},"link":null},{"localized_name":"enable_debug","name":"enable_debug","shape":7,"type":"BOOLEAN","widget":{"name":"enable_debug"},"link":null}],"outputs":[{"localized_name":"IMAGE","name":"IMAGE","type":"IMAGE","links":[81]}],"properties":{"cnr_id":"seedvr2_videoupscaler","ver":"690cc39379c1481159ddd451368dbf2295930fc6","Node name for S&R":"SeedVR2VideoUpscaler","aux_id":"ainvfx/ComfyUI-SeedVR2_VideoUpscaler"},"widgets_values":[42,"fixed",1024,0,33,true,"lab",3,0,0,0,"cuda:0",false]},{"id":248,"type":"GetNode","pos":[7412.729190518597,-638.6814668898652],"size":[210,60],"flags":{},"order":3,"mode":2,"inputs":[],"outputs":[{"name":"AUDIO","type":"AUDIO","links":[272]}],"title":"Get_UpscaleVideo_Audio","properties":{},"widgets_values":["UpscaleVideo_Audio"]},{"id":249,"type":"GetNode","pos":[7404.326133509962,-533.3035035660946],"size":[210,58],"flags":{},"order":4,"mode":2,"inputs":[],"outputs":[{"name":"FLOAT","type":"FLOAT","links":[273]}],"title":"Get_UpscaleVideo_fps","properties":{},"widgets_values":["UpscaleVideo_fps"],"color":"#232","bgcolor":"#353"},{"id":206,"type":"GetImagesFromBatchIndexed","pos":[6421.201093154646,-505.48498432494114],"size":[250.665625,88],"flags":{},"order":54,"mode":2,"inputs":[{"localized_name":"images","name":"images","type":"IMAGE","link":215},{"localized_name":"indexes","name":"indexes","type":"STRING","widget":{"name":"indexes"},"link":null}],"outputs":[{"localized_name":"IMAGE","name":"IMAGE","type":"IMAGE","links":[216]}],"properties":{"cnr_id":"comfyui-kjnodes","ver":"50a0837f9aea602b184bbf6dbabf66ed2c7a1d22","Node name for S&R":"GetImagesFromBatchIndexed"},"widgets_values":["0"]},{"id":254,"type":"GetNode","pos":[4938.933279030173,-402.8094702807197],"size":[210,58],"flags":{},"order":5,"mode":0,"inputs":[],"outputs":[{"name":"FLOAT","type":"FLOAT","links":[279]}],"title":"Get_UpscaleVideo_fps","properties":{},"widgets_values":["UpscaleVideo_fps"],"color":"#232","bgcolor":"#353"},{"id":253,"type":"GetNode","pos":[4947.3363360388075,-508.1874336044904],"size":[210,58],"flags":{},"order":6,"mode":0,"inputs":[],"outputs":[{"name":"AUDIO","type":"AUDIO","links":[278]}],"title":"Get_UpscaleVideo_Audio","properties":{},"widgets_values":["UpscaleVideo_Audio"]},{"id":196,"type":"PrimitiveString","pos":[7344.564294013713,-404.05210130771667],"size":[270,58],"flags":{},"order":7,"mode":2,"inputs":[{"localized_name":"value","name":"value","type":"STRING","widget":{"name":"value"},"link":null}],"outputs":[{"localized_name":"STRING","name":"STRING","type":"STRING","links":[207]}],"title":"String - FolderName","properties":{"cnr_id":"comfy-core","ver":"0.12.3","Node name for S&R":"PrimitiveString"},"widgets_values":["MiracleCreationStudio/Upscale_Face/"],"color":"#322","bgcolor":"#533"},{"id":199,"type":"JoinStrings","pos":[7785.220451996916,-413.8899762712968],"size":[270,78],"flags":{},"order":39,"mode":2,"inputs":[{"localized_name":"string1","name":"string1","shape":7,"type":"STRING","link":207},{"localized_name":"string2","name":"string2","shape":7,"type":"STRING","link":276},{"localized_name":"delimiter","name":"delimiter","type":"STRING","widget":{"name":"delimiter"},"link":null}],"outputs":[{"localized_name":"STRING","name":"STRING","type":"STRING","links":[206,212]}],"properties":{"cnr_id":"comfyui-kjnodes","ver":"50a0837f9aea602b184bbf6dbabf66ed2c7a1d22","Node name for S&R":"JoinStrings"},"widgets_values":[""]},{"id":237,"type":"SetNode","pos":[3097.4938012199673,-613.8172467300702],"size":[210,58],"flags":{},"order":70,"mode":0,"inputs":[{"name":"AUDIO","type":"AUDIO","link":260}],"outputs":[{"name":"*","type":"*","links":null}],"title":"Set_UpscaleVideo_Audio","properties":{"previousName":"UpscaleVideo_Audio"},"widgets_values":["UpscaleVideo_Audio"]},{"id":255,"type":"GetNode","pos":[4848.2299075520705,-109.51666575553116],"size":[210,60],"flags":{},"order":8,"mode":0,"inputs":[],"outputs":[{"name":"STRING","type":"STRING","links":[280]}],"title":"Get_FileName_Upscale","properties":{},"widgets_values":["FileName_Upscale"]},{"id":246,"type":"GetNode","pos":[6751.823334834131,-664.0848409905167],"size":[210,58],"flags":{"collapsed":false},"order":9,"mode":2,"inputs":[],"outputs":[{"name":"SEEDVR2_DIT","type":"SEEDVR2_DIT","links":[268]}],"title":"Get_Upscale_DiTModel","properties":{},"widgets_values":["Upscale_DiTModel"]},{"id":61,"type":"ImageCrop+","pos":[6421.872646829628,-734.8405288969191],"size":[224.83072916666669,194],"flags":{},"order":38,"mode":2,"inputs":[{"localized_name":"image","name":"image","type":"IMAGE","link":271},{"localized_name":"width","name":"width","type":"INT","widget":{"name":"width"},"link":null},{"localized_name":"height","name":"height","type":"INT","widget":{"name":"height"},"link":null},{"localized_name":"position","name":"position","type":"COMBO","widget":{"name":"position"},"link":null},{"localized_name":"x_offset","name":"x_offset","type":"INT","widget":{"name":"x_offset"},"link":null},{"localized_name":"y_offset","name":"y_offset","type":"INT","widget":{"name":"y_offset"},"link":null}],"outputs":[{"localized_name":"IMAGE","name":"IMAGE","type":"IMAGE","links":[215,277]},{"localized_name":"x","name":"x","type":"INT","links":null},{"localized_name":"y","name":"y","type":"INT","links":null}],"properties":{"cnr_id":"comfyui_essentials_mb","ver":"1.1.2","Node name for S&R":"ImageCrop+"},"widgets_values":[256,256,"center",0,-450]},{"id":67,"type":"CreateVideo","pos":[7774.6438186258265,-723.8257476427322],"size":[269.7916666666667,78],"flags":{"collapsed":false},"order":74,"mode":2,"inputs":[{"localized_name":"images","name":"images","type":"IMAGE","link":81},{"localized_name":"audio","name":"audio","shape":7,"type":"AUDIO","link":272},{"localized_name":"fps","name":"fps","type":"FLOAT","widget":{"name":"fps"},"link":273}],"outputs":[{"localized_name":"VIDEO","name":"VIDEO","type":"VIDEO","links":[80]}],"properties":{"cnr_id":"comfy-core","ver":"0.3.68","Node name for S&R":"CreateVideo"},"widgets_values":[24]},{"id":209,"type":"GetVideoComponents","pos":[2680.901751651951,-630.7128766025621],"size":[282.8125,66],"flags":{},"order":52,"mode":0,"inputs":[{"localized_name":"video","name":"video","type":"VIDEO","link":235}],"outputs":[{"localized_name":"images","name":"images","type":"IMAGE","links":[259]},{"localized_name":"audio","name":"audio","type":"AUDIO","links":[260]},{"localized_name":"fps","name":"fps","type":"FLOAT","links":[261]}],"properties":{"cnr_id":"comfy-core","ver":"0.3.68","Node name for S&R":"GetVideoComponents"},"widgets_values":[]},{"id":238,"type":"SetNode","pos":[3098.1294276029425,-507.72381142279767],"size":[210,58],"flags":{},"order":71,"mode":0,"inputs":[{"name":"FLOAT","type":"FLOAT","link":261}],"outputs":[{"name":"*","type":"*","links":null}],"title":"Set_UpscaleVideo_fps","properties":{"previousName":"UpscaleVideo_fps"},"widgets_values":["UpscaleVideo_fps"],"color":"#232","bgcolor":"#353"},{"id":66,"type":"SaveVideo","pos":[8150.144046336689,-726.649416377751],"size":[269.7916666666667,367.7916666666667],"flags":{},"order":84,"mode":2,"inputs":[{"localized_name":"video","name":"video","type":"VIDEO","link":80},{"localized_name":"filename_prefix","name":"filename_prefix","type":"STRING","widget":{"name":"filename_prefix"},"link":212},{"localized_name":"format","name":"format","type":"COMBO","widget":{"name":"format"},"link":null},{"localized_name":"codec","name":"codec","type":"COMBO","widget":{"name":"codec"},"link":null}],"outputs":[],"properties":{"cnr_id":"comfy-core","ver":"0.3.68","Node name for S&R":"SaveVideo"},"widgets_values":["video/A_720p_SeedVR2_128to1024","mp4","h264"],"shape":2},{"id":236,"type":"SetNode","pos":[3095.2216675681757,-724.4701967119873],"size":[213.7310546875,60],"flags":{},"order":69,"mode":0,"inputs":[{"name":"IMAGE","type":"IMAGE","link":259}],"outputs":[{"name":"*","type":"*","links":null}],"title":"Set_UpscaleVideo_Images","properties":{"previousName":"UpscaleVideo_Images"},"widgets_values":["UpscaleVideo_Images"],"color":"#2a363b","bgcolor":"#3f5159"},{"id":271,"type":"easy showAnything","pos":[3381.595094900122,-164.0917877536125],"size":[210,88],"flags":{},"order":95,"mode":0,"inputs":[{"localized_name":"anything","name":"anything","shape":7,"type":"*","link":291}],"outputs":[{"localized_name":"output","name":"output","type":"*","links":null}],"properties":{"cnr_id":"comfyui-easy-use","ver":"7c470c67d6df44498e52c902173c1ac77cd5bdfd","Node name for S&R":"easy showAnything"},"widgets_values":["Upscale_ExperienceGuide_00"]},{"id":263,"type":"StringReplace","pos":[3026.738748486768,-235.37998114980513],"size":[244.58401885917738,196],"flags":{},"order":72,"mode":0,"inputs":[{"localized_name":"string","name":"string","type":"STRING","widget":{"name":"string"},"link":284},{"localized_name":"find","name":"find","type":"STRING","widget":{"name":"find"},"link":null},{"localized_name":"replace","name":"replace","type":"STRING","widget":{"name":"replace"},"link":null}],"outputs":[{"localized_name":"STRING","name":"STRING","type":"STRING","links":[288,292]}],"properties":{"cnr_id":"comfy-core","ver":"0.12.3","Node name for S&R":"StringReplace"},"widgets_values":["",".mp4",""]},{"id":265,"type":"JoinStrings","pos":[3377.7021068892423,-288.64166408343624],"size":[270,78],"flags":{},"order":82,"mode":0,"inputs":[{"localized_name":"string1","name":"string1","shape":7,"type":"STRING","link":287},{"localized_name":"string2","name":"string2","shape":7,"type":"STRING","link":288},{"localized_name":"delimiter","name":"delimiter","type":"STRING","widget":{"name":"delimiter"},"link":null}],"outputs":[{"localized_name":"STRING","name":"STRING","type":"STRING","links":[289,291]}],"properties":{"cnr_id":"comfyui-kjnodes","ver":"50a0837f9aea602b184bbf6dbabf66ed2c7a1d22","Node name for S&R":"JoinStrings"},"widgets_values":["_"]},{"id":250,"type":"SetNode","pos":[3668.062481674566,-295.4137828994838],"size":[210,60],"flags":{},"order":94,"mode":0,"inputs":[{"name":"STRING","type":"STRING","link":289}],"outputs":[{"name":"*","type":"*","links":[]}],"title":"Set_FileName_Upscale","properties":{"previousName":"FileName_Upscale"},"widgets_values":["FileName_Upscale"]},{"id":240,"type":"SetNode","pos":[4468.652337158243,-113.57406641178949],"size":[210,60],"flags":{"collapsed":false},"order":46,"mode":0,"inputs":[{"name":"SEEDVR2_DIT","type":"SEEDVR2_DIT","link":263}],"outputs":[{"name":"*","type":"*","links":null}],"title":"Set_Upscale_DiTModel","properties":{"previousName":"Upscale_DiTModel"},"widgets_values":["Upscale_DiTModel"]},{"id":241,"type":"SetNode","pos":[4475.831590643794,149.27687265051281],"size":[210,58],"flags":{"collapsed":false},"order":40,"mode":0,"inputs":[{"name":"SEEDVR2_VAE","type":"SEEDVR2_VAE","link":264}],"outputs":[{"name":"*","type":"*","links":null}],"title":"Set_Upscale_VAEModel","properties":{"previousName":"Upscale_VAEModel"},"widgets_values":["Upscale_VAEModel"]},{"id":62,"type":"PreviewImage","pos":[6427.142858420556,-382.3494172260461],"size":[187.5,267.5],"flags":{},"order":73,"mode":2,"inputs":[{"localized_name":"images","name":"images","type":"IMAGE","link":216}],"outputs":[],"properties":{"cnr_id":"comfy-core","ver":"0.11.1","Node name for S&R":"PreviewImage"},"widgets_values":[]},{"id":244,"type":"GetNode","pos":[6753.678357363681,-556.1476342723561],"size":[210,58],"flags":{"collapsed":false},"order":10,"mode":2,"inputs":[],"outputs":[{"name":"SEEDVR2_VAE","type":"SEEDVR2_VAE","links":[281]}],"title":"Get_Upscale_VAEModel","properties":{},"widgets_values":["Upscale_VAEModel"]},{"id":267,"type":"PrimitiveString","pos":[3030.122867958543,-335.15184337220813],"size":[234.2696355055141,58],"flags":{},"order":11,"mode":0,"inputs":[{"localized_name":"value","name":"value","type":"STRING","widget":{"name":"value"},"link":null}],"outputs":[{"localized_name":"STRING","name":"STRING","type":"STRING","links":[287]}],"properties":{"cnr_id":"comfy-core","ver":"0.12.3","Node name for S&R":"PrimitiveString"},"widgets_values":["Upscale"]},{"id":277,"type":"WidgetToString","pos":[289.5735183692358,-739.6396121746375],"size":[294.341796875,154],"flags":{},"order":44,"mode":0,"inputs":[{"localized_name":"any_input","name":"any_input","shape":7,"type":"*","link":302},{"localized_name":"id","name":"id","type":"INT","widget":{"name":"id"},"link":null},{"localized_name":"widget_name","name":"widget_name","type":"STRING","widget":{"name":"widget_name"},"link":null},{"localized_name":"return_all","name":"return_all","type":"BOOLEAN","widget":{"name":"return_all"},"link":null},{"localized_name":"node_title","name":"node_title","shape":7,"type":"STRING","widget":{"name":"node_title"},"link":null},{"localized_name":"allowed_float_decimals","name":"allowed_float_decimals","shape":7,"type":"INT","widget":{"name":"allowed_float_decimals"},"link":null}],"outputs":[{"localized_name":"STRING","name":"STRING","type":"STRING","links":[297]}],"properties":{"cnr_id":"comfyui-kjnodes","ver":"50a0837f9aea602b184bbf6dbabf66ed2c7a1d22","Node name for S&R":"WidgetToString"},"widgets_values":[0,"file",false,"",2]},{"id":162,"type":"JoinStrings","pos":[1593.8844238360152,-81.66476056819232],"size":[270,78],"flags":{},"order":42,"mode":0,"inputs":[{"localized_name":"string1","name":"string1","shape":7,"type":"STRING","link":161},{"localized_name":"string2","name":"string2","shape":7,"type":"STRING","link":307},{"localized_name":"delimiter","name":"delimiter","type":"STRING","widget":{"name":"delimiter"},"link":null}],"outputs":[{"localized_name":"STRING","name":"STRING","type":"STRING","links":[308,309]}],"properties":{"cnr_id":"comfyui-kjnodes","ver":"50a0837f9aea602b184bbf6dbabf66ed2c7a1d22","Node name for S&R":"JoinStrings"},"widgets_values":[""]},{"id":272,"type":"easy showAnything","pos":[3031.861201952953,-5.77439367593246],"size":[210,88],"flags":{},"order":83,"mode":0,"inputs":[{"localized_name":"anything","name":"anything","shape":7,"type":"*","link":292}],"outputs":[{"localized_name":"output","name":"output","type":"*","links":null}],"properties":{"cnr_id":"comfyui-easy-use","ver":"7c470c67d6df44498e52c902173c1ac77cd5bdfd","Node name for S&R":"easy showAnything"},"widgets_values":["ExperienceGuide_00"]},{"id":247,"type":"GetNode","pos":[6155.128657321896,-730.3386361169331],"size":[215.1939453125,58],"flags":{},"order":12,"mode":2,"inputs":[],"outputs":[{"name":"IMAGE","type":"IMAGE","links":[271]}],"title":"Get_UpscaleVideo_Images","properties":{},"widgets_values":["UpscaleVideo_Images"],"color":"#2a363b","bgcolor":"#3f5159"},{"id":252,"type":"GetNode","pos":[7342.237705618182,-293.0414686147428],"size":[210,60],"flags":{},"order":13,"mode":2,"inputs":[],"outputs":[{"name":"STRING","type":"STRING","links":[276]}],"title":"Get_FileName_Upscale","properties":{},"widgets_values":["FileName_Upscale"]},{"id":219,"type":"SeedVR2LoadVAEModel","pos":[4063.1302617650604,146.71658943085077],"size":[312.63020833333337,298],"flags":{},"order":14,"mode":0,"inputs":[{"localized_name":"torch_compile_args","name":"torch_compile_args","shape":7,"type":"TORCH_COMPILE_ARGS","link":null},{"localized_name":"model","name":"model","type":"COMBO","widget":{"name":"model"},"link":null},{"localized_name":"device","name":"device","type":"COMBO","widget":{"name":"device"},"link":null},{"localized_name":"encode_tiled","name":"encode_tiled","shape":7,"type":"BOOLEAN","widget":{"name":"encode_tiled"},"link":null},{"localized_name":"encode_tile_size","name":"encode_tile_size","shape":7,"type":"INT","widget":{"name":"encode_tile_size"},"link":null},{"localized_name":"encode_tile_overlap","name":"encode_tile_overlap","shape":7,"type":"INT","widget":{"name":"encode_tile_overlap"},"link":null},{"localized_name":"decode_tiled","name":"decode_tiled","shape":7,"type":"BOOLEAN","widget":{"name":"decode_tiled"},"link":null},{"localized_name":"decode_tile_size","name":"decode_tile_size","shape":7,"type":"INT","widget":{"name":"decode_tile_size"},"link":null},{"localized_name":"decode_tile_overlap","name":"decode_tile_overlap","shape":7,"type":"INT","widget":{"name":"decode_tile_overlap"},"link":null},{"localized_name":"tile_debug","name":"tile_debug","shape":7,"type":"COMBO","widget":{"name":"tile_debug"},"link":null},{"localized_name":"offload_device","name":"offload_device","shape":7,"type":"COMBO","widget":{"name":"offload_device"},"link":null},{"localized_name":"cache_model","name":"cache_model","shape":7,"type":"BOOLEAN","widget":{"name":"cache_model"},"link":null}],"outputs":[{"localized_name":"SEEDVR2_VAE","name":"SEEDVR2_VAE","type":"SEEDVR2_VAE","links":[264]}],"properties":{"cnr_id":"seedvr2_videoupscaler","ver":"690cc39379c1481159ddd451368dbf2295930fc6","Node name for S&R":"SeedVR2LoadVAEModel","aux_id":"ainvfx/ComfyUI-SeedVR2_VideoUpscaler"},"widgets_values":["ema_vae_fp16.safetensors","cuda:0",true,1024,128,true,768,128,"false","cpu",false]},{"id":222,"type":"GetVideoComponents","pos":[240.7784344697234,-291.73767452688577],"size":[193.530859375,66],"flags":{},"order":43,"mode":0,"inputs":[{"localized_name":"video","name":"video","type":"VIDEO","link":242}],"outputs":[{"localized_name":"images","name":"images","type":"IMAGE","links":[243,245]},{"localized_name":"audio","name":"audio","type":"AUDIO","links":[]},{"localized_name":"fps","name":"fps","type":"FLOAT","links":[249,294]}],"properties":{"cnr_id":"comfy-core","ver":"0.12.3","Node name for S&R":"GetVideoComponents"},"widgets_values":[]},{"id":130,"type":"FILM VFI","pos":[1240.2641964363656,-294.88079126447894],"size":[321.77083333333337,126],"flags":{},"order":96,"mode":0,"inputs":[{"localized_name":"frames","name":"frames","type":"IMAGE","link":122},{"localized_name":"optional_interpolation_states","name":"optional_interpolation_states","shape":7,"type":"INTERPOLATION_STATES","link":null},{"localized_name":"ckpt_name","name":"ckpt_name","type":"COMBO","widget":{"name":"ckpt_name"},"link":null},{"localized_name":"clear_cache_after_n_frames","name":"clear_cache_after_n_frames","type":"INT","widget":{"name":"clear_cache_after_n_frames"},"link":null},{"localized_name":"multiplier","name":"multiplier","type":"INT","widget":{"name":"multiplier"},"link":295}],"outputs":[{"localized_name":"IMAGE","name":"IMAGE","type":"IMAGE","links":[250]}],"properties":{"cnr_id":"comfyui-frame-interpolation","ver":"1.0.7","Node name for S&R":"FILM VFI"},"widgets_values":["film_net_fp32.pt",11,48]},{"id":164,"type":"easy showAnything","pos":[1595.6201665783806,33.142494292425496],"size":[267.3066040039066,98.87998657226558],"flags":{},"order":58,"mode":0,"inputs":[{"localized_name":"anything","name":"anything","shape":7,"type":"*","link":308}],"outputs":[{"localized_name":"output","name":"output","type":"*","links":[]}],"properties":{"cnr_id":"comfyui-easy-use","ver":"7c470c67d6df44498e52c902173c1ac77cd5bdfd","Node name for S&R":"easy showAnything"},"widgets_values":["MiracleCreationStudio/Morph/UpscaleMorph_Idle_Tilt"]},{"id":280,"type":"SetNode","pos":[1915.9799573565297,-749.8050829736619],"size":[210,58],"flags":{},"order":107,"mode":0,"inputs":[{"name":"STRING","type":"STRING","link":300}],"outputs":[{"name":"*","type":"*","links":[]}],"title":"Set_FileName_Morph","properties":{"previousName":"FileName_Morph"},"widgets_values":["FileName_Morph"]},{"id":274,"type":"MathExpression|pysssss","pos":[710.1818770881005,-12.17317696845115],"size":[249.2371217957509,128],"flags":{},"order":61,"mode":0,"inputs":[{"localized_name":"a","name":"a","shape":7,"type":"INT,FLOAT,IMAGE,LATENT","link":294},{"localized_name":"b","name":"b","shape":7,"type":"INT,FLOAT,IMAGE,LATENT","link":null},{"localized_name":"c","name":"c","shape":7,"type":"INT,FLOAT,IMAGE,LATENT","link":null},{"localized_name":"expression","name":"expression","type":"INT,FLOAT,IMAGE,LATENT","widget":{"name":"expression"},"link":null}],"outputs":[{"localized_name":"INT","name":"INT","type":"INT","links":[295]},{"localized_name":"FLOAT","name":"FLOAT","type":"FLOAT","links":null}],"properties":{"cnr_id":"comfyui-custom-scripts","ver":"1.2.5"},"widgets_values":["a * 2"]},{"id":286,"type":"MarkdownNote","pos":[8129.473028080838,-306.8931287285725],"size":[492.70175074934616,104.25914614762996],"flags":{},"order":15,"mode":0,"inputs":[],"outputs":[],"properties":{},"widgets_values":["# 파일 이름 수정 필요\n"],"color":"#432","bgcolor":"#653"},{"id":211,"type":"SeedVR2VideoUpscaler","pos":[4443.440771580188,-625.0250858319599],"size":[269.956640625,386],"flags":{},"order":45,"mode":0,"inputs":[{"localized_name":"image","name":"image","type":"IMAGE","link":262},{"localized_name":"dit","name":"dit","type":"SEEDVR2_DIT","link":265},{"localized_name":"vae","name":"vae","type":"SEEDVR2_VAE","link":266},{"localized_name":"seed","name":"seed","type":"INT","widget":{"name":"seed"},"link":null},{"localized_name":"resolution","name":"resolution","type":"INT","widget":{"name":"resolution"},"link":null},{"localized_name":"max_resolution","name":"max_resolution","type":"INT","widget":{"name":"max_resolution"},"link":null},{"localized_name":"batch_size","name":"batch_size","type":"INT","widget":{"name":"batch_size"},"link":null},{"localized_name":"uniform_batch_size","name":"uniform_batch_size","type":"BOOLEAN","widget":{"name":"uniform_batch_size"},"link":null},{"localized_name":"color_correction","name":"color_correction","type":"COMBO","widget":{"name":"color_correction"},"link":null},{"localized_name":"temporal_overlap","name":"temporal_overlap","shape":7,"type":"INT","widget":{"name":"temporal_overlap"},"link":null},{"localized_name":"prepend_frames","name":"prepend_frames","shape":7,"type":"INT","widget":{"name":"prepend_frames"},"link":null},{"localized_name":"input_noise_scale","name":"input_noise_scale","shape":7,"type":"FLOAT","widget":{"name":"input_noise_scale"},"link":null},{"localized_name":"latent_noise_scale","name":"latent_noise_scale","shape":7,"type":"FLOAT","widget":{"name":"latent_noise_scale"},"link":null},{"localized_name":"offload_device","name":"offload_device","shape":7,"type":"COMBO","widget":{"name":"offload_device"},"link":null},{"localized_name":"enable_debug","name":"enable_debug","shape":7,"type":"BOOLEAN","widget":{"name":"enable_debug"},"link":null}],"outputs":[{"localized_name":"IMAGE","name":"IMAGE","type":"IMAGE","links":[218]}],"properties":{"cnr_id":"seedvr2_videoupscaler","ver":"690cc39379c1481159ddd451368dbf2295930fc6","Node name for S&R":"SeedVR2VideoUpscaler","aux_id":"ainvfx/ComfyUI-SeedVR2_VideoUpscaler"},"widgets_values":[42,"fixed",1080,0,33,true,"lab",3,0,0,0,"cuda:0",false]},{"id":279,"type":"JoinStrings","pos":[1609.8600102899147,-744.6089574565419],"size":[270,78],"flags":{},"order":97,"mode":0,"inputs":[{"localized_name":"string1","name":"string1","shape":7,"type":"STRING","link":298},{"localized_name":"string2","name":"string2","shape":7,"type":"STRING","link":333},{"localized_name":"delimiter","name":"delimiter","type":"STRING","widget":{"name":"delimiter"},"link":null}],"outputs":[{"localized_name":"STRING","name":"STRING","type":"STRING","links":[296,300]}],"properties":{"cnr_id":"comfyui-kjnodes","ver":"50a0837f9aea602b184bbf6dbabf66ed2c7a1d22","Node name for S&R":"JoinStrings"},"widgets_values":["_"]},{"id":308,"type":"StringReplace","pos":[1210.3631439833487,-640.1009659170276],"size":[244.58401885917738,196],"flags":{},"order":87,"mode":0,"inputs":[{"localized_name":"string","name":"string","type":"STRING","widget":{"name":"string"},"link":332},{"localized_name":"find","name":"find","type":"STRING","widget":{"name":"find"},"link":null},{"localized_name":"replace","name":"replace","type":"STRING","widget":{"name":"replace"},"link":null}],"outputs":[{"localized_name":"STRING","name":"STRING","type":"STRING","links":[333]}],"properties":{"cnr_id":"comfy-core","ver":"0.12.3","Node name for S&R":"StringReplace"},"widgets_values":["",".mp4",""]},{"id":282,"type":"StringReplace","pos":[925.2740858486611,-639.6286840356731],"size":[244.58401885917738,196],"flags":{},"order":76,"mode":0,"inputs":[{"localized_name":"string","name":"string","type":"STRING","widget":{"name":"string"},"link":303},{"localized_name":"find","name":"find","type":"STRING","widget":{"name":"find"},"link":null},{"localized_name":"replace","name":"replace","type":"STRING","widget":{"name":"replace"},"link":null}],"outputs":[{"localized_name":"STRING","name":"STRING","type":"STRING","links":[332]}],"properties":{"cnr_id":"comfy-core","ver":"0.12.3","Node name for S&R":"StringReplace"},"widgets_values":["","_00001_",""]},{"id":198,"type":"easy showAnything","pos":[7782.316122143561,-299.1464659059178],"size":[267.3066040039066,98.87998657226558],"flags":{},"order":56,"mode":2,"inputs":[{"localized_name":"anything","name":"anything","shape":7,"type":"*","link":206}],"outputs":[{"localized_name":"output","name":"output","type":"*","links":null}],"properties":{"cnr_id":"comfyui-easy-use","ver":"7c470c67d6df44498e52c902173c1ac77cd5bdfd","Node name for S&R":"easy showAnything"},"widgets_values":["MiracleCreationStudio/Upscale_Face/Idle_Tilt"]},{"id":261,"type":"WidgetToString","pos":[2688.7532183454096,-215.37954371958338],"size":[294.341796875,154],"flags":{},"order":53,"mode":0,"inputs":[{"localized_name":"any_input","name":"any_input","shape":7,"type":"*","link":282},{"localized_name":"id","name":"id","type":"INT","widget":{"name":"id"},"link":null},{"localized_name":"widget_name","name":"widget_name","type":"STRING","widget":{"name":"widget_name"},"link":null},{"localized_name":"return_all","name":"return_all","type":"BOOLEAN","widget":{"name":"return_all"},"link":null},{"localized_name":"node_title","name":"node_title","shape":7,"type":"STRING","widget":{"name":"node_title"},"link":null},{"localized_name":"allowed_float_decimals","name":"allowed_float_decimals","shape":7,"type":"INT","widget":{"name":"allowed_float_decimals"},"link":null}],"outputs":[{"localized_name":"STRING","name":"STRING","type":"STRING","links":[284]}],"properties":{"cnr_id":"comfyui-kjnodes","ver":"50a0837f9aea602b184bbf6dbabf66ed2c7a1d22","Node name for S&R":"WidgetToString"},"widgets_values":[0,"file",false,"",2]},{"id":80,"type":"GroundingDinoModelLoader (segment anything)","pos":[1155.0226192234725,1444.9755726351948],"size":[359.398046875,58],"flags":{},"order":16,"mode":0,"inputs":[{"localized_name":"model_name","name":"model_name","type":"COMBO","widget":{"name":"model_name"},"link":null}],"outputs":[{"localized_name":"GROUNDING_DINO_MODEL","name":"GROUNDING_DINO_MODEL","type":"GROUNDING_DINO_MODEL","links":[96]}],"properties":{"cnr_id":"comfyui_segment_anything","ver":"ab6395596399d5048639cdab7e44ec9fae857a93","Node name for S&R":"GroundingDinoModelLoader (segment anything)"},"widgets_values":["GroundingDINO_SwinT_OGC (694MB)"]},{"id":278,"type":"StringReplace","pos":[648.6166258050262,-641.9658157481888],"size":[244.58401885917738,196],"flags":{},"order":62,"mode":0,"inputs":[{"localized_name":"string","name":"string","type":"STRING","widget":{"name":"string"},"link":297},{"localized_name":"find","name":"find","type":"STRING","widget":{"name":"find"},"link":null},{"localized_name":"replace","name":"replace","type":"STRING","widget":{"name":"replace"},"link":null}],"outputs":[{"localized_name":"STRING","name":"STRING","type":"STRING","links":[303]}],"properties":{"cnr_id":"comfy-core","ver":"0.12.3","Node name for S&R":"StringReplace"},"widgets_values":["","Upscale_",""]},{"id":330,"type":"StringReplace","pos":[1433.856970206678,2300.3745149290608],"size":[244.58401885917738,196.00000000000006],"flags":{},"order":68,"mode":0,"inputs":[{"localized_name":"string","name":"string","type":"STRING","widget":{"name":"string"},"link":354},{"localized_name":"find","name":"find","type":"STRING","widget":{"name":"find"},"link":null},{"localized_name":"replace","name":"replace","type":"STRING","widget":{"name":"replace"},"link":null}],"outputs":[{"localized_name":"STRING","name":"STRING","type":"STRING","links":[348]}],"properties":{"cnr_id":"comfy-core","ver":"0.12.3","Node name for S&R":"StringReplace"},"widgets_values":["","_00001_",""]},{"id":132,"type":"PrimitiveString","pos":[1238.1402488432468,-47.37390804065045],"size":[270,58],"flags":{},"order":17,"mode":0,"inputs":[{"localized_name":"value","name":"value","type":"STRING","widget":{"name":"value"},"link":null}],"outputs":[{"localized_name":"STRING","name":"STRING","type":"STRING","links":[161]}],"title":"String - FolderName","properties":{"cnr_id":"comfy-core","ver":"0.12.3","Node name for S&R":"PrimitiveString"},"widgets_values":["MiracleCreationStudio/Morph/"],"color":"#322","bgcolor":"#533"},{"id":332,"type":"JoinStrings","pos":[2012.5831520491258,2296.6007746677283],"size":[270,78],"flags":{},"order":93,"mode":0,"inputs":[{"localized_name":"string1","name":"string1","shape":7,"type":"STRING","link":350},{"localized_name":"string2","name":"string2","shape":7,"type":"STRING","link":351},{"localized_name":"delimiter","name":"delimiter","type":"STRING","widget":{"name":"delimiter"},"link":null}],"outputs":[{"localized_name":"STRING","name":"STRING","type":"STRING","links":[352,358]}],"properties":{"cnr_id":"comfyui-kjnodes","ver":"50a0837f9aea602b184bbf6dbabf66ed2c7a1d22","Node name for S&R":"JoinStrings"},"widgets_values":["_"]},{"id":331,"type":"PrimitiveString","pos":[1731.861606838384,2167.278407481604],"size":[234.2696355055141,58],"flags":{},"order":18,"mode":0,"inputs":[{"localized_name":"value","name":"value","type":"STRING","widget":{"name":"value"},"link":null}],"outputs":[{"localized_name":"STRING","name":"STRING","type":"STRING","links":[350]}],"properties":{"cnr_id":"comfy-core","ver":"0.12.3","Node name for S&R":"PrimitiveString"},"widgets_values":["Mask"]},{"id":87,"type":"PreviewImage","pos":[801.4560643130051,1519.2291270271078],"size":[279.7916666666667,353.02083333333337],"flags":{},"order":92,"mode":0,"inputs":[{"localized_name":"images","name":"images","type":"IMAGE","link":101}],"outputs":[],"properties":{"cnr_id":"comfy-core","ver":"0.11.1","Node name for S&R":"PreviewImage"},"widgets_values":[]},{"id":324,"type":"MarkdownNote","pos":[-295.70110814090873,2087.0365225881114],"size":[580.6307098133944,165.4598972056906],"flags":{},"order":19,"mode":0,"inputs":[],"outputs":[],"properties":{},"widgets_values":["# Load Video (VHS)로 불러오면 색감 변형 이슈 있음.\n# 순수 Load Video로 불러오면 색감 유지. (로딩 더 느린 느낌)\n\n# 지금은 마스크만 뽑을거라서 굳이 변형돼도 상관없음"],"color":"#432","bgcolor":"#653"},{"id":334,"type":"PrimitiveString","pos":[2317.6867188931583,2203.486524556317],"size":[270,58],"flags":{},"order":20,"mode":0,"inputs":[{"localized_name":"value","name":"value","type":"STRING","widget":{"name":"value"},"link":null}],"outputs":[{"localized_name":"STRING","name":"STRING","type":"STRING","links":[355]}],"title":"String - FolderName","properties":{"cnr_id":"comfy-core","ver":"0.12.3","Node name for S&R":"PrimitiveString"},"widgets_values":["MiracleCreationStudio/Mask/"],"color":"#322","bgcolor":"#533"},{"id":329,"type":"StringReplace","pos":[1718.9460283413669,2299.9022330477064],"size":[244.58401885917738,196.00000000000006],"flags":{},"order":81,"mode":0,"inputs":[{"localized_name":"string","name":"string","type":"STRING","widget":{"name":"string"},"link":348},{"localized_name":"find","name":"find","type":"STRING","widget":{"name":"find"},"link":null},{"localized_name":"replace","name":"replace","type":"STRING","widget":{"name":"replace"},"link":null}],"outputs":[{"localized_name":"STRING","name":"STRING","type":"STRING","links":[351]}],"properties":{"cnr_id":"comfy-core","ver":"0.12.3","Node name for S&R":"StringReplace"},"widgets_values":["",".mp4",""]},{"id":214,"type":"PrimitiveString","pos":[4812.017557395597,-221.9926472491832],"size":[270,58],"flags":{},"order":21,"mode":0,"inputs":[{"localized_name":"value","name":"value","type":"STRING","widget":{"name":"value"},"link":null}],"outputs":[{"localized_name":"STRING","name":"STRING","type":"STRING","links":[224]}],"title":"String - FolderName","properties":{"cnr_id":"comfy-core","ver":"0.12.3","Node name for S&R":"PrimitiveString"},"widgets_values":["MiracleCreationStudio/Upscale/"],"color":"#322","bgcolor":"#533"},{"id":142,"type":"Fast Groups Muter (rgthree)","pos":[-941.1036282203628,-463.789886849409],"size":[560.411177002209,274],"flags":{},"order":22,"mode":0,"inputs":[],"outputs":[{"name":"OPT_CONNECTION","type":"*","links":null}],"properties":{"matchColors":"","matchTitle":"","showNav":true,"showAllGraphs":true,"sort":"position","customSortAlphabet":"","toggleRestriction":"default"}},{"id":212,"type":"JoinStrings","pos":[5126.6257643539875,-196.62041026692393],"size":[270,78],"flags":{},"order":41,"mode":0,"inputs":[{"localized_name":"string1","name":"string1","shape":7,"type":"STRING","link":224},{"localized_name":"string2","name":"string2","shape":7,"type":"STRING","link":280},{"localized_name":"delimiter","name":"delimiter","type":"STRING","widget":{"name":"delimiter"},"link":null}],"outputs":[{"localized_name":"STRING","name":"STRING","type":"STRING","links":[217,227]}],"properties":{"cnr_id":"comfyui-kjnodes","ver":"50a0837f9aea602b184bbf6dbabf66ed2c7a1d22","Node name for S&R":"JoinStrings"},"widgets_values":[""]},{"id":224,"type":"ReverseImageBatch","pos":[489.0860603011109,-284.43391163489474],"size":[179.421484375,26],"flags":{},"order":60,"mode":0,"inputs":[{"localized_name":"images","name":"images","type":"IMAGE","link":245}],"outputs":[{"localized_name":"IMAGE","name":"IMAGE","type":"IMAGE","links":[246]}],"properties":{"cnr_id":"comfyui-kjnodes","ver":"50a0837f9aea602b184bbf6dbabf66ed2c7a1d22","Node name for S&R":"ReverseImageBatch"},"widgets_values":[]},{"id":336,"type":"easy showAnything","pos":[2640.0974491728907,2389.4099973570133],"size":[267.3066040039066,98.87998657226558],"flags":{},"order":113,"mode":0,"inputs":[{"localized_name":"anything","name":"anything","shape":7,"type":"*","link":357}],"outputs":[{"localized_name":"output","name":"output","type":"*","links":[]}],"properties":{"cnr_id":"comfyui-easy-use","ver":"7c470c67d6df44498e52c902173c1ac77cd5bdfd","Node name for S&R":"easy showAnything"},"widgets_values":["MiracleCreationStudio/Mask/Mask_ExperienceGuide_00"]},{"id":133,"type":"BatchImagesNode","pos":[1010.9795780972377,-230.98601452843363],"size":[187.5,66],"flags":{},"order":85,"mode":0,"inputs":[{"label":"image0","localized_name":"images.image0","name":"images.image0","type":"IMAGE","link":247},{"label":"image1","localized_name":"images.image1","name":"images.image1","type":"IMAGE","link":248},{"label":"image2","localized_name":"images.image2","name":"images.image2","shape":7,"type":"IMAGE","link":null}],"outputs":[{"localized_name":"IMAGE","name":"IMAGE","type":"IMAGE","links":[122]}],"properties":{"cnr_id":"comfy-core","ver":"0.11.0","Node name for S&R":"BatchImagesNode"},"widgets_values":[]},{"id":223,"type":"GetImagesFromBatchIndexed","pos":[709.5224324934977,-147.4046600003711],"size":[250.665625,88],"flags":{},"order":59,"mode":0,"inputs":[{"localized_name":"images","name":"images","type":"IMAGE","link":243},{"localized_name":"indexes","name":"indexes","type":"STRING","widget":{"name":"indexes"},"link":null}],"outputs":[{"localized_name":"IMAGE","name":"IMAGE","type":"IMAGE","links":[248]}],"properties":{"cnr_id":"comfyui-kjnodes","ver":"50a0837f9aea602b184bbf6dbabf66ed2c7a1d22","Node name for S&R":"GetImagesFromBatchIndexed"},"widgets_values":["0"]},{"id":284,"type":"GetNode","pos":[1278.425006140118,58.95364197212662],"size":[210,60],"flags":{},"order":23,"mode":0,"inputs":[],"outputs":[{"name":"STRING","type":"STRING","links":[307]}],"title":"Get_FileName_Morph","properties":{},"widgets_values":["FileName_Morph"]},{"id":226,"type":"CreateVideo","pos":[1602.5402528208838,-302.3505047084676],"size":[270,78],"flags":{},"order":105,"mode":0,"inputs":[{"localized_name":"images","name":"images","type":"IMAGE","link":250},{"localized_name":"audio","name":"audio","shape":7,"type":"AUDIO","link":null},{"localized_name":"fps","name":"fps","type":"FLOAT","widget":{"name":"fps"},"link":249}],"outputs":[{"localized_name":"VIDEO","name":"VIDEO","type":"VIDEO","links":[251]}],"properties":{"cnr_id":"comfy-core","ver":"0.12.3","Node name for S&R":"CreateVideo"},"widgets_values":[24]},{"id":225,"type":"GetImagesFromBatchIndexed","pos":[721.090875165228,-294.8740656438184],"size":[250.665625,88],"flags":{},"order":75,"mode":0,"inputs":[{"localized_name":"images","name":"images","type":"IMAGE","link":246},{"localized_name":"indexes","name":"indexes","type":"STRING","widget":{"name":"indexes"},"link":null}],"outputs":[{"localized_name":"IMAGE","name":"IMAGE","type":"IMAGE","links":[247,370]}],"properties":{"cnr_id":"comfyui-kjnodes","ver":"50a0837f9aea602b184bbf6dbabf66ed2c7a1d22","Node name for S&R":"GetImagesFromBatchIndexed"},"widgets_values":["10"]},{"id":275,"type":"PrimitiveString","pos":[681.9156891135906,-766.9872874724133],"size":[234.2696355055141,58],"flags":{},"order":24,"mode":0,"inputs":[{"localized_name":"value","name":"value","type":"STRING","widget":{"name":"value"},"link":null}],"outputs":[{"localized_name":"STRING","name":"STRING","type":"STRING","links":[298]}],"properties":{"cnr_id":"comfy-core","ver":"0.12.3","Node name for S&R":"PrimitiveString"},"widgets_values":["Morph"]},{"id":221,"type":"LoadVideo","pos":[-134.16747886541435,-751.6406727419039],"size":[273.8541666666667,658.2222222222222],"flags":{},"order":25,"mode":0,"inputs":[{"localized_name":"file","name":"file","type":"COMBO","widget":{"name":"file"},"link":null},{"localized_name":"choose file to upload","name":"upload","type":"IMAGEUPLOAD","widget":{"name":"upload"},"link":null}],"outputs":[{"localized_name":"VIDEO","name":"VIDEO","type":"VIDEO","links":[242,302]}],"properties":{"cnr_id":"comfy-core","ver":"0.3.68","Node name for S&R":"LoadVideo"},"widgets_values":["Idle_TiltSmile.mp4","image"]},{"id":345,"type":"PreviewImage","pos":[1057.9311292885457,208.21240241633538],"size":[140,246],"flags":{},"order":86,"mode":0,"inputs":[{"localized_name":"images","name":"images","type":"IMAGE","link":370}],"outputs":[],"properties":{"cnr_id":"comfy-core","ver":"0.12.3","Node name for S&R":"PreviewImage"},"widgets_values":[]},{"id":187,"type":"MarkdownNote","pos":[-261.6612404028243,-35.27431639319432],"size":[492.70175074934616,104.25914614762996],"flags":{},"order":26,"mode":0,"inputs":[],"outputs":[],"properties":{},"widgets_values":["# Load Video (VHS)로 불러오면 색감 변형 이슈 있음.\n# 순수 Load Video로 불러오면 색감 유지."],"color":"#432","bgcolor":"#653"},{"id":276,"type":"easy showAnything","pos":[1613.7529983007946,-621.4992024107112],"size":[210,88],"flags":{},"order":106,"mode":0,"inputs":[{"localized_name":"anything","name":"anything","shape":7,"type":"*","link":296}],"outputs":[{"localized_name":"output","name":"output","type":"*","links":null}],"properties":{"cnr_id":"comfyui-easy-use","ver":"7c470c67d6df44498e52c902173c1ac77cd5bdfd","Node name for S&R":"easy showAnything"},"widgets_values":["Morph_Idle_TiltSmile"]},{"id":207,"type":"easy showAnything","pos":[5126.823291249552,-77.96752777054661],"size":[267.3066040039066,98.87998657226558],"flags":{},"order":57,"mode":0,"inputs":[{"localized_name":"anything","name":"anything","shape":7,"type":"*","link":217}],"outputs":[{"localized_name":"output","name":"output","type":"*","links":null}],"properties":{"cnr_id":"comfyui-easy-use","ver":"7c470c67d6df44498e52c902173c1ac77cd5bdfd","Node name for S&R":"easy showAnything"},"widgets_values":["MiracleCreationStudio/Upscale/Upscale_ExperienceGuide_00"]},{"id":333,"type":"easy showAnything","pos":[2016.4761400600057,2419.710529713559],"size":[210,88],"flags":{},"order":103,"mode":0,"inputs":[{"localized_name":"anything","name":"anything","shape":7,"type":"*","link":352}],"outputs":[{"localized_name":"output","name":"output","type":"*","links":null}],"properties":{"cnr_id":"comfyui-easy-use","ver":"7c470c67d6df44498e52c902173c1ac77cd5bdfd","Node name for S&R":"easy showAnything"},"widgets_values":["Mask_Idle_Tilt"]},{"id":227,"type":"SaveVideo","pos":[1931.377215377233,-306.07597737873346],"size":[269.7916666666667,577.6296296296297],"flags":{},"order":114,"mode":0,"inputs":[{"localized_name":"video","name":"video","type":"VIDEO","link":251},{"localized_name":"filename_prefix","name":"filename_prefix","type":"STRING","widget":{"name":"filename_prefix"},"link":309},{"localized_name":"format","name":"format","type":"COMBO","widget":{"name":"format"},"link":null},{"localized_name":"codec","name":"codec","type":"COMBO","widget":{"name":"codec"},"link":null}],"outputs":[],"properties":{"cnr_id":"comfy-core","ver":"0.3.68","Node name for S&R":"SaveVideo"},"widgets_values":["video/A_720p_SeedVR2_128to1024","mp4","h264"],"shape":2},{"id":348,"type":"MaskToImage","pos":[2358.7228727109236,2966.074905031211],"size":[193.2779296875,26],"flags":{},"order":99,"mode":0,"inputs":[{"localized_name":"mask","name":"mask","type":"MASK","link":371}],"outputs":[{"localized_name":"IMAGE","name":"IMAGE","type":"IMAGE","links":[372]}],"properties":{"cnr_id":"comfy-core","ver":"0.6.0","Node name for S&R":"MaskToImage"},"widgets_values":[]},{"id":362,"type":"StringReplace","pos":[1392.2497354409313,4265.985180533314],"size":[244.58401885917738,196.00000000000006],"flags":{},"order":65,"mode":0,"inputs":[{"localized_name":"string","name":"string","type":"STRING","widget":{"name":"string"},"link":385},{"localized_name":"find","name":"find","type":"STRING","widget":{"name":"find"},"link":null},{"localized_name":"replace","name":"replace","type":"STRING","widget":{"name":"replace"},"link":null}],"outputs":[{"localized_name":"STRING","name":"STRING","type":"STRING","links":[388]}],"properties":{"cnr_id":"comfy-core","ver":"0.12.3","Node name for S&R":"StringReplace"},"widgets_values":["","_00001_",""]},{"id":364,"type":"PrimitiveString","pos":[1677.3387935756202,4133.361354967211],"size":[234.2696355055141,58],"flags":{},"order":27,"mode":0,"inputs":[{"localized_name":"value","name":"value","type":"STRING","widget":{"name":"value"},"link":null}],"outputs":[{"localized_name":"STRING","name":"STRING","type":"STRING","links":[386]}],"properties":{"cnr_id":"comfy-core","ver":"0.12.3","Node name for S&R":"PrimitiveString"},"widgets_values":["Mask"]},{"id":366,"type":"StringReplace","pos":[1677.3387935756202,4265.985180533314],"size":[244.58401885917738,196.00000000000006],"flags":{},"order":79,"mode":0,"inputs":[{"localized_name":"string","name":"string","type":"STRING","widget":{"name":"string"},"link":388},{"localized_name":"find","name":"find","type":"STRING","widget":{"name":"find"},"link":null},{"localized_name":"replace","name":"replace","type":"STRING","widget":{"name":"replace"},"link":null}],"outputs":[{"localized_name":"STRING","name":"STRING","type":"STRING","links":[387]}],"properties":{"cnr_id":"comfy-core","ver":"0.12.3","Node name for S&R":"StringReplace"},"widgets_values":["",".mp4",""]},{"id":369,"type":"easy showAnything","pos":[1970.9759172833792,4385.793477199167],"size":[210,88],"flags":{},"order":100,"mode":0,"inputs":[{"localized_name":"anything","name":"anything","shape":7,"type":"*","link":390}],"outputs":[{"localized_name":"output","name":"output","type":"*","links":null}],"properties":{"cnr_id":"comfyui-easy-use","ver":"7c470c67d6df44498e52c902173c1ac77cd5bdfd","Node name for S&R":"easy showAnything"},"widgets_values":["Mask_Idle_Tilt"]},{"id":370,"type":"JoinStrings","pos":[2596.697494328219,4239.408304831685],"size":[270,78],"flags":{},"order":101,"mode":0,"inputs":[{"localized_name":"string1","name":"string1","shape":7,"type":"STRING","link":391},{"localized_name":"string2","name":"string2","shape":7,"type":"STRING","link":392},{"localized_name":"delimiter","name":"delimiter","type":"STRING","widget":{"name":"delimiter"},"link":null}],"outputs":[{"localized_name":"STRING","name":"STRING","type":"STRING","links":[389,394]}],"properties":{"cnr_id":"comfyui-kjnodes","ver":"50a0837f9aea602b184bbf6dbabf66ed2c7a1d22","Node name for S&R":"JoinStrings"},"widgets_values":[""]},{"id":367,"type":"WidgetToString","pos":[899.2264286910918,4265.985180533314],"size":[294.341796875,154],"flags":{},"order":49,"mode":0,"inputs":[{"localized_name":"any_input","name":"any_input","shape":7,"type":"*","link":393},{"localized_name":"id","name":"id","type":"INT","widget":{"name":"id"},"link":null},{"localized_name":"widget_name","name":"widget_name","type":"STRING","widget":{"name":"widget_name"},"link":null},{"localized_name":"return_all","name":"return_all","type":"BOOLEAN","widget":{"name":"return_all"},"link":null},{"localized_name":"node_title","name":"node_title","shape":7,"type":"STRING","widget":{"name":"node_title"},"link":null},{"localized_name":"allowed_float_decimals","name":"allowed_float_decimals","shape":7,"type":"INT","widget":{"name":"allowed_float_decimals"},"link":null}],"outputs":[{"localized_name":"STRING","name":"STRING","type":"STRING","links":[385]}],"properties":{"cnr_id":"comfyui-kjnodes","ver":"50a0837f9aea602b184bbf6dbabf66ed2c7a1d22","Node name for S&R":"WidgetToString"},"widgets_values":[0,"file",false,"",2]},{"id":368,"type":"easy showAnything","pos":[2598.4902144071443,4355.49294484262],"size":[267.3066040039066,98.87998657226558],"flags":{},"order":110,"mode":0,"inputs":[{"localized_name":"anything","name":"anything","shape":7,"type":"*","link":389}],"outputs":[{"localized_name":"output","name":"output","type":"*","links":[]}],"properties":{"cnr_id":"comfyui-easy-use","ver":"7c470c67d6df44498e52c902173c1ac77cd5bdfd","Node name for S&R":"easy showAnything"},"widgets_values":["MiracleCreationStudio/Mask/Mask_Idle_Tilt"]},{"id":239,"type":"GetNode","pos":[4061.3599835143204,-699.2525813143562],"size":[215.1939453125,60],"flags":{},"order":28,"mode":0,"inputs":[],"outputs":[{"name":"IMAGE","type":"IMAGE","links":[262]}],"title":"Get_UpscaleVideo_Images","properties":{},"widgets_values":["UpscaleVideo_Images"],"color":"#2a363b","bgcolor":"#3f5159"},{"id":208,"type":"SeedVR2LoadDiTModel","pos":[4064.6532127022942,-113.93396456860572],"size":[307.43489583333337,202],"flags":{},"order":29,"mode":0,"inputs":[{"localized_name":"torch_compile_args","name":"torch_compile_args","shape":7,"type":"TORCH_COMPILE_ARGS","link":null},{"localized_name":"model","name":"model","type":"COMBO","widget":{"name":"model"},"link":null},{"localized_name":"device","name":"device","type":"COMBO","widget":{"name":"device"},"link":null},{"localized_name":"blocks_to_swap","name":"blocks_to_swap","shape":7,"type":"INT","widget":{"name":"blocks_to_swap"},"link":null},{"localized_name":"swap_io_components","name":"swap_io_components","shape":7,"type":"BOOLEAN","widget":{"name":"swap_io_components"},"link":null},{"localized_name":"offload_device","name":"offload_device","shape":7,"type":"COMBO","widget":{"name":"offload_device"},"link":null},{"localized_name":"cache_model","name":"cache_model","shape":7,"type":"BOOLEAN","widget":{"name":"cache_model"},"link":null},{"localized_name":"attention_mode","name":"attention_mode","shape":7,"type":"COMBO","widget":{"name":"attention_mode"},"link":null}],"outputs":[{"localized_name":"SEEDVR2_DIT","name":"SEEDVR2_DIT","type":"SEEDVR2_DIT","links":[263]}],"properties":{"cnr_id":"seedvr2_videoupscaler","ver":"690cc39379c1481159ddd451368dbf2295930fc6","Node name for S&R":"SeedVR2LoadDiTModel","aux_id":"ainvfx/ComfyUI-SeedVR2_VideoUpscaler"},"widgets_values":["seedvr2_ema_3b_fp16.safetensors","cuda:0",32,false,"cpu",false,"sdpa"]},{"id":210,"type":"CreateVideo","pos":[5212.143930919225,-626.8219807391141],"size":[269.7916666666667,78],"flags":{"collapsed":false},"order":63,"mode":0,"inputs":[{"localized_name":"images","name":"images","type":"IMAGE","link":218},{"localized_name":"audio","name":"audio","shape":7,"type":"AUDIO","link":278},{"localized_name":"fps","name":"fps","type":"FLOAT","widget":{"name":"fps"},"link":279}],"outputs":[{"localized_name":"VIDEO","name":"VIDEO","type":"VIDEO","links":[226]}],"properties":{"cnr_id":"comfy-core","ver":"0.3.68","Node name for S&R":"CreateVideo"},"widgets_values":[24]},{"id":363,"type":"JoinStrings","pos":[1970.9759172833792,4253.187202197089],"size":[270,78],"flags":{},"order":90,"mode":0,"inputs":[{"localized_name":"string1","name":"string1","shape":7,"type":"STRING","link":386},{"localized_name":"string2","name":"string2","shape":7,"type":"STRING","link":387},{"localized_name":"delimiter","name":"delimiter","type":"STRING","widget":{"name":"delimiter"},"link":null}],"outputs":[{"localized_name":"STRING","name":"STRING","type":"STRING","links":[390,392]}],"properties":{"cnr_id":"comfyui-kjnodes","ver":"50a0837f9aea602b184bbf6dbabf66ed2c7a1d22","Node name for S&R":"JoinStrings"},"widgets_values":["_"]},{"id":365,"type":"PrimitiveString","pos":[2267.63799888319,4147.410965728951],"size":[270,58],"flags":{},"order":30,"mode":0,"inputs":[{"localized_name":"value","name":"value","type":"STRING","widget":{"name":"value"},"link":null}],"outputs":[{"localized_name":"STRING","name":"STRING","type":"STRING","links":[391]}],"title":"String - FolderName","properties":{"cnr_id":"comfy-core","ver":"0.12.3","Node name for S&R":"PrimitiveString"},"widgets_values":["MiracleCreationStudio/Mask/"],"color":"#322","bgcolor":"#533"},{"id":353,"type":"GetVideoComponents","pos":[242.77573177890739,3057.318004917453],"size":[193.530859375,66],"flags":{},"order":48,"mode":0,"inputs":[{"localized_name":"video","name":"video","type":"VIDEO","link":376}],"outputs":[{"localized_name":"images","name":"images","type":"IMAGE","links":[396]},{"localized_name":"audio","name":"audio","type":"AUDIO","links":null},{"localized_name":"fps","name":"fps","type":"FLOAT","links":[373,378]}],"properties":{"cnr_id":"comfy-core","ver":"0.7.0","Node name for S&R":"GetVideoComponents"},"widgets_values":[]},{"id":350,"type":"VideoMaMaPipelineLoader","pos":[1696.7689549725053,2725.3039346135106],"size":[261.9018433018282,226],"flags":{},"order":31,"mode":0,"inputs":[{"localized_name":"base_model_path","name":"base_model_path","type":"STRING","widget":{"name":"base_model_path"},"link":null},{"localized_name":"unet_checkpoint_path","name":"unet_checkpoint_path","type":"STRING","widget":{"name":"unet_checkpoint_path"},"link":null},{"localized_name":"precision","name":"precision","type":"COMBO","widget":{"name":"precision"},"link":null},{"localized_name":"enable_model_cpu_offload","name":"enable_model_cpu_offload","type":"BOOLEAN","widget":{"name":"enable_model_cpu_offload"},"link":null},{"localized_name":"vae_encode_chunk_size","name":"vae_encode_chunk_size","type":"INT","widget":{"name":"vae_encode_chunk_size"},"link":null},{"localized_name":"attention_mode","name":"attention_mode","type":"COMBO","widget":{"name":"attention_mode"},"link":null},{"localized_name":"enable_vae_tiling","name":"enable_vae_tiling","type":"BOOLEAN","widget":{"name":"enable_vae_tiling"},"link":null},{"localized_name":"enable_vae_slicing","name":"enable_vae_slicing","type":"BOOLEAN","widget":{"name":"enable_vae_slicing"},"link":null}],"outputs":[{"localized_name":"VIDEOMAMA_PIPELINE","name":"VIDEOMAMA_PIPELINE","type":"VIDEOMAMA_PIPELINE","links":[380]}],"properties":{"cnr_id":"ComfyUI-VideoMaMa","ver":"bb6ad06aab8ec947892f0b9207f01deb93f61720","Node name for S&R":"VideoMaMaPipelineLoader","aux_id":"okdalto/ComfyUI-VideoMaMa"},"widgets_values":["checkpoints/stabilityai/stable-video-diffusion-img2vid-xt","checkpoints/VideoMaMa","fp16",true,4,"auto",false,true]},{"id":352,"type":"SaveVideo","pos":[1698.5913974340028,3314.2604022219057],"size":[270,578],"flags":{},"order":108,"mode":0,"inputs":[{"localized_name":"video","name":"video","type":"VIDEO","link":375},{"localized_name":"filename_prefix","name":"filename_prefix","type":"STRING","widget":{"name":"filename_prefix"},"link":null},{"localized_name":"format","name":"format","type":"COMBO","widget":{"name":"format"},"link":null},{"localized_name":"codec","name":"codec","type":"COMBO","widget":{"name":"codec"},"link":null}],"outputs":[],"properties":{"cnr_id":"comfy-core","ver":"0.7.0","Node name for S&R":"SaveVideo"},"widgets_values":["video/ComfyUI","auto","auto"]},{"id":357,"type":"VideoMaMaSampler","pos":[2041.8691769236714,2966.074905031211],"size":[273.705078125,218],"flags":{},"order":89,"mode":0,"inputs":[{"localized_name":"pipeline","name":"pipeline","type":"VIDEOMAMA_PIPELINE","link":380},{"localized_name":"images","name":"images","type":"IMAGE","link":398},{"localized_name":"masks","name":"masks","type":"MASK","link":382},{"localized_name":"seed","name":"seed","type":"INT","widget":{"name":"seed"},"link":null},{"localized_name":"max_resolution","name":"max_resolution","type":"INT","widget":{"name":"max_resolution"},"link":null},{"localized_name":"fps","name":"fps","type":"INT","widget":{"name":"fps"},"link":null},{"localized_name":"motion_bucket_id","name":"motion_bucket_id","type":"INT","widget":{"name":"motion_bucket_id"},"link":null},{"localized_name":"noise_aug_strength","name":"noise_aug_strength","type":"FLOAT","widget":{"name":"noise_aug_strength"},"link":null}],"outputs":[{"localized_name":"MASK","name":"MASK","type":"MASK","links":[371]}],"properties":{"cnr_id":"ComfyUI-VideoMaMa","ver":"89c0eb6862ca89f07da8b0da6a17c846f196f084","Node name for S&R":"VideoMaMaSampler","aux_id":"okdalto/ComfyUI-VideoMaMa"},"widgets_values":[669659046717278,"fixed",1024,4,127,0]},{"id":372,"type":"ImageScale","pos":[604.9041463826314,2895.4750570983224],"size":[270,130],"flags":{},"order":64,"mode":0,"inputs":[{"localized_name":"image","name":"image","type":"IMAGE","link":396},{"localized_name":"upscale_method","name":"upscale_method","type":"COMBO","widget":{"name":"upscale_method"},"link":null},{"localized_name":"width","name":"width","type":"INT","widget":{"name":"width"},"link":null},{"localized_name":"height","name":"height","type":"INT","widget":{"name":"height"},"link":null},{"localized_name":"crop","name":"crop","type":"COMBO","widget":{"name":"crop"},"link":null}],"outputs":[{"localized_name":"IMAGE","name":"IMAGE","type":"IMAGE","links":[397,398]}],"properties":{"cnr_id":"comfy-core","ver":"0.12.3","Node name for S&R":"ImageScale"},"widgets_values":["nearest-exact",576,1024,"disabled"]},{"id":351,"type":"MaskToImage","pos":[1064.293872957275,3300.972803239246],"size":[193.2779296875,26],"flags":{},"order":88,"mode":0,"inputs":[{"localized_name":"mask","name":"mask","type":"MASK","link":374}],"outputs":[{"localized_name":"IMAGE","name":"IMAGE","type":"IMAGE","links":[377]}],"properties":{"cnr_id":"comfy-core","ver":"0.6.0","Node name for S&R":"MaskToImage"},"widgets_values":[]},{"id":355,"type":"CreateVideo","pos":[1307.335256116651,3375.961877122948],"size":[270,78],"flags":{},"order":98,"mode":0,"inputs":[{"localized_name":"images","name":"images","type":"IMAGE","link":377},{"localized_name":"audio","name":"audio","shape":7,"type":"AUDIO","link":null},{"localized_name":"fps","name":"fps","type":"FLOAT","widget":{"name":"fps"},"link":378}],"outputs":[{"localized_name":"VIDEO","name":"VIDEO","type":"VIDEO","links":[375]}],"properties":{"cnr_id":"comfy-core","ver":"0.7.0","Node name for S&R":"CreateVideo"},"widgets_values":[30]},{"id":356,"type":"SAM2VideoMaskGenerator","pos":[1008.6519082103783,3112.1614895066887],"size":[374.83777949543935,106],"flags":{},"order":78,"mode":0,"inputs":[{"localized_name":"images","name":"images","type":"IMAGE","link":397},{"localized_name":"checkpoint_path","name":"checkpoint_path","type":"STRING","widget":{"name":"checkpoint_path"},"link":null},{"localized_name":"config_name","name":"config_name","type":"STRING","widget":{"name":"config_name"},"link":null}],"outputs":[{"localized_name":"MASK","name":"MASK","type":"MASK","links":[374,382]}],"properties":{"cnr_id":"ComfyUI-VideoMaMa","ver":"b15acfc820de2010e92eb95e4f12c4fce5ea4195","Node name for S&R":"SAM2VideoMaskGenerator"},"widgets_values":["checkpoints/sam2/sam2.1_hiera_large.pt","configs/sam2.1/sam2.1_hiera_l.yaml"],"sam2PointData":{"points_x":"349,351,301,425,346,348,249,463,494,215,297,425,400,334,319,416,359,345,356,303,401,123,629,356,94,633,626,116","points_y":"412,536,689,694,333,269,368,371,484,487,893,900,1189,1182,1073,1075,633,117,194,243,245,1157,1172,1262,200,200,845,841","labels":"1,1,1,1,1,1,1,1,1,1,1,1,1,1,1,1,1,1,1,1,1,0,0,0,0,0,0,0"}},{"id":323,"type":"VHS_LoadVideo","pos":[-845.4761823097078,1286.5227784923347],"size":[261.6533203125,310],"flags":{},"order":32,"mode":0,"inputs":[{"localized_name":"meta_batch","name":"meta_batch","shape":7,"type":"VHS_BatchManager","link":null},{"localized_name":"vae","name":"vae","shape":7,"type":"VAE","link":null},{"localized_name":"video","name":"video","type":"COMBO","widget":{"name":"video"},"link":null},{"localized_name":"force_rate","name":"force_rate","type":"FLOAT","widget":{"name":"force_rate"},"link":null},{"localized_name":"custom_width","name":"custom_width","type":"INT","widget":{"name":"custom_width"},"link":null},{"localized_name":"custom_height","name":"custom_height","type":"INT","widget":{"name":"custom_height"},"link":null},{"localized_name":"frame_load_cap","name":"frame_load_cap","type":"INT","widget":{"name":"frame_load_cap"},"link":null},{"localized_name":"skip_first_frames","name":"skip_first_frames","type":"INT","widget":{"name":"skip_first_frames"},"link":null},{"localized_name":"select_every_nth","name":"select_every_nth","type":"INT","widget":{"name":"select_every_nth"},"link":null},{"localized_name":"format","name":"format","shape":7,"type":"COMBO","widget":{"name":"format"},"link":null}],"outputs":[{"localized_name":"IMAGE","name":"IMAGE","type":"IMAGE","links":[]},{"localized_name":"frame_count","name":"frame_count","type":"INT","links":null},{"localized_name":"audio","name":"audio","type":"AUDIO","links":null},{"localized_name":"video_info","name":"video_info","type":"VHS_VIDEOINFO","links":[343]}],"properties":{"cnr_id":"comfyui-videohelpersuite","ver":"993082e4f2473bf4acaf06f51e33877a7eb38960","Node name for S&R":"VHS_LoadVideo"},"widgets_values":{"video":"Idle_WaveBoth.mp4","force_rate":0,"custom_width":0,"custom_height":0,"frame_load_cap":0,"skip_first_frames":0,"select_every_nth":1,"format":"AnimateDiff","videopreview":{"hidden":false,"paused":false,"params":{"filename":"Idle_WaveBoth.mp4","type":"input","format":"video/mp4","force_rate":0,"custom_width":0,"custom_height":0,"frame_load_cap":0,"skip_first_frames":0,"select_every_nth":1}}}},{"id":327,"type":"WidgetToString","pos":[940.8336634568384,2326.668505282973],"size":[294.341796875,154],"flags":{},"order":51,"mode":0,"inputs":[{"localized_name":"any_input","name":"any_input","shape":7,"type":"*","link":404},{"localized_name":"id","name":"id","type":"INT","widget":{"name":"id"},"link":null},{"localized_name":"widget_name","name":"widget_name","type":"STRING","widget":{"name":"widget_name"},"link":null},{"localized_name":"return_all","name":"return_all","type":"BOOLEAN","widget":{"name":"return_all"},"link":null},{"localized_name":"node_title","name":"node_title","shape":7,"type":"STRING","widget":{"name":"node_title"},"link":null},{"localized_name":"allowed_float_decimals","name":"allowed_float_decimals","shape":7,"type":"INT","widget":{"name":"allowed_float_decimals"},"link":null}],"outputs":[{"localized_name":"STRING","name":"STRING","type":"STRING","links":[354]}],"properties":{"cnr_id":"comfyui-kjnodes","ver":"50a0837f9aea602b184bbf6dbabf66ed2c7a1d22","Node name for S&R":"WidgetToString"},"widgets_values":[0,"file",false,"",2]},{"id":325,"type":"VHS_VideoInfo","pos":[-514.5892105390377,1303.040281992713],"size":[234.931640625,206],"flags":{},"order":47,"mode":0,"inputs":[{"localized_name":"video_info","name":"video_info","type":"VHS_VIDEOINFO","link":343}],"outputs":[{"localized_name":"source_fps🟨","name":"source_fps🟨","type":"FLOAT","links":[]},{"localized_name":"source_frame_count🟨","name":"source_frame_count🟨","type":"INT","links":null},{"localized_name":"source_duration🟨","name":"source_duration🟨","type":"FLOAT","links":null},{"localized_name":"source_width🟨","name":"source_width🟨","type":"INT","links":null},{"localized_name":"source_height🟨","name":"source_height🟨","type":"INT","links":null},{"localized_name":"loaded_fps🟦","name":"loaded_fps🟦","type":"FLOAT","links":null},{"localized_name":"loaded_frame_count🟦","name":"loaded_frame_count🟦","type":"INT","links":null},{"localized_name":"loaded_duration🟦","name":"loaded_duration🟦","type":"FLOAT","links":null},{"localized_name":"loaded_width🟦","name":"loaded_width🟦","type":"INT","links":null},{"localized_name":"loaded_height🟦","name":"loaded_height🟦","type":"INT","links":null}],"properties":{"cnr_id":"comfyui-videohelpersuite","ver":"993082e4f2473bf4acaf06f51e33877a7eb38960","Node name for S&R":"VHS_VideoInfo"},"widgets_values":{}},{"id":373,"type":"GetVideoComponents","pos":[221.4479789650231,1267.2541572862222],"size":[193.530859375,66],"flags":{},"order":50,"mode":0,"inputs":[{"localized_name":"video","name":"video","type":"VIDEO","link":399}],"outputs":[{"localized_name":"images","name":"images","type":"IMAGE","links":[400]},{"localized_name":"audio","name":"audio","type":"AUDIO","links":null},{"localized_name":"fps","name":"fps","type":"FLOAT","links":[403]}],"properties":{"cnr_id":"comfy-core","ver":"0.7.0","Node name for S&R":"GetVideoComponents"},"widgets_values":[]},{"id":72,"type":"GetImagesFromBatchIndexed","pos":[1155.0226192234725,1553.0709981441566],"size":[353.24699182396614,88],"flags":{},"order":91,"mode":0,"inputs":[{"localized_name":"images","name":"images","type":"IMAGE","link":87},{"localized_name":"indexes","name":"indexes","type":"STRING","widget":{"name":"indexes"},"link":null}],"outputs":[{"localized_name":"IMAGE","name":"IMAGE","type":"IMAGE","slot_index":0,"links":[97]}],"properties":{"cnr_id":"comfyui-kjnodes","ver":"16a335c8c40b1b3eef8b770022276004d5bea66b","Node name for S&R":"GetImagesFromBatchIndexed"},"widgets_values":["0"],"color":"#223","bgcolor":"#335"},{"id":79,"type":"GroundingDinoSAMSegment (segment anything)","pos":[1677.4200680650586,1282.7350066049514],"size":[362.214453125,122],"flags":{},"order":102,"mode":0,"inputs":[{"localized_name":"sam_model","name":"sam_model","type":"SAM_MODEL","link":95},{"localized_name":"grounding_dino_model","name":"grounding_dino_model","type":"GROUNDING_DINO_MODEL","link":96},{"localized_name":"image","name":"image","type":"IMAGE","link":97},{"localized_name":"prompt","name":"prompt","type":"STRING","widget":{"name":"prompt"},"link":null},{"localized_name":"threshold","name":"threshold","type":"FLOAT","widget":{"name":"threshold"},"link":null}],"outputs":[{"localized_name":"IMAGE","name":"IMAGE","type":"IMAGE","links":[]},{"localized_name":"MASK","name":"MASK","type":"MASK","links":[88,94]}],"properties":{"cnr_id":"comfyui_segment_anything","ver":"ab6395596399d5048639cdab7e44ec9fae857a93","Node name for S&R":"GroundingDinoSAMSegment (segment anything)"},"widgets_values":["character",0.3]},{"id":339,"type":"SetNode","pos":[464.66149114943516,1446.3990320582811],"size":[210,60],"flags":{},"order":67,"mode":0,"inputs":[{"name":"FLOAT","type":"FLOAT","link":403}],"outputs":[{"name":"*","type":"*","links":null}],"title":"Set_Mask_FPS","properties":{"previousName":"Mask_FPS"},"widgets_values":["Mask_FPS"],"color":"#232","bgcolor":"#353"},{"id":349,"type":"CreateVideo","pos":[2573.2541840836293,2966.074905031211],"size":[270,78],"flags":{},"order":109,"mode":0,"inputs":[{"localized_name":"images","name":"images","type":"IMAGE","link":372},{"localized_name":"audio","name":"audio","shape":7,"type":"AUDIO","link":null},{"localized_name":"fps","name":"fps","type":"FLOAT","widget":{"name":"fps"},"link":373}],"outputs":[{"localized_name":"VIDEO","name":"VIDEO","type":"VIDEO","links":[383]}],"properties":{"cnr_id":"comfy-core","ver":"0.6.0","Node name for S&R":"CreateVideo"},"widgets_values":[30]},{"id":78,"type":"MatAnyoneVideoMatting","pos":[2195.752954564379,1282.7350066049514],"size":[380.3125,198],"flags":{},"order":112,"mode":0,"inputs":[{"localized_name":"video_frames","name":"video_frames","type":"IMAGE","link":93},{"localized_name":"mask","name":"mask","type":"MASK","link":94},{"localized_name":"warmup_frames","name":"warmup_frames","type":"INT","widget":{"name":"warmup_frames"},"link":null},{"localized_name":"erode_kernel","name":"erode_kernel","type":"INT","widget":{"name":"erode_kernel"},"link":null},{"localized_name":"dilate_kernel","name":"dilate_kernel","type":"INT","widget":{"name":"dilate_kernel"},"link":null},{"localized_name":"bg_red","name":"bg_red","type":"INT","widget":{"name":"bg_red"},"link":null},{"localized_name":"bg_green","name":"bg_green","type":"INT","widget":{"name":"bg_green"},"link":null},{"localized_name":"bg_blue","name":"bg_blue","type":"INT","widget":{"name":"bg_blue"},"link":null}],"outputs":[{"localized_name":"foreground_frames","name":"foreground_frames","type":"IMAGE","slot_index":0,"links":[407]},{"localized_name":"alpha_frames","name":"alpha_frames","type":"MASK","slot_index":1,"links":[89]}],"properties":{"aux_id":"KytraScript/ComfyUI_MatAnyone_Kytra","ver":"ac2c6e45a6b8b093292a4ecc8740a0694305a2f1","Node name for S&R":"MatAnyoneVideoMatting"},"widgets_values":[10,10,10,0,255,0],"color":"#322","bgcolor":"#533"},{"id":335,"type":"JoinStrings","pos":[2638.3047290939653,2273.3253573460784],"size":[270,78],"flags":{},"order":104,"mode":0,"inputs":[{"localized_name":"string1","name":"string1","shape":7,"type":"STRING","link":355},{"localized_name":"string2","name":"string2","shape":7,"type":"STRING","link":358},{"localized_name":"delimiter","name":"delimiter","type":"STRING","widget":{"name":"delimiter"},"link":null}],"outputs":[{"localized_name":"STRING","name":"STRING","type":"STRING","links":[357,411]}],"properties":{"cnr_id":"comfyui-kjnodes","ver":"50a0837f9aea602b184bbf6dbabf66ed2c7a1d22","Node name for S&R":"JoinStrings"},"widgets_values":[""]},{"id":378,"type":"GetNode","pos":[3109.163987966212,1371.8619317035834],"size":[210,58],"flags":{},"order":33,"mode":0,"inputs":[],"outputs":[{"name":"FLOAT","type":"FLOAT","links":[406]}],"title":"Get_Mask_FPS","properties":{},"widgets_values":["Mask_FPS"],"color":"#232","bgcolor":"#353"},{"id":377,"type":"CreateVideo","pos":[3393.556686274675,1927.2853606082517],"size":[270,78],"flags":{},"order":117,"mode":0,"inputs":[{"localized_name":"images","name":"images","type":"IMAGE","link":407},{"localized_name":"audio","name":"audio","shape":7,"type":"AUDIO","link":null},{"localized_name":"fps","name":"fps","type":"FLOAT","widget":{"name":"fps"},"link":405}],"outputs":[{"localized_name":"VIDEO","name":"VIDEO","type":"VIDEO","links":[412]}],"properties":{"cnr_id":"comfy-core","ver":"0.6.0","Node name for S&R":"CreateVideo"},"widgets_values":[30]},{"id":340,"type":"GetNode","pos":[3135.792124495673,1953.0667879524797],"size":[210,60],"flags":{},"order":34,"mode":0,"inputs":[],"outputs":[{"name":"FLOAT","type":"FLOAT","links":[405]}],"title":"Get_Mask_FPS","properties":{},"widgets_values":["Mask_FPS"],"color":"#232","bgcolor":"#353"},{"id":74,"type":"MaskToImage","pos":[2700.8970995865648,1282.8286806529934],"size":[282.08333333333337,26],"flags":{},"order":118,"mode":0,"inputs":[{"localized_name":"mask","name":"mask","type":"MASK","link":89}],"outputs":[{"localized_name":"IMAGE","name":"IMAGE","type":"IMAGE","slot_index":0,"links":[408]}],"properties":{"cnr_id":"comfy-core","ver":"0.11.1","Node name for S&R":"MaskToImage"},"widgets_values":[],"color":"#323","bgcolor":"#535"},{"id":376,"type":"CreateVideo","pos":[3381.619216503361,1284.6735636758517],"size":[270,78],"flags":{},"order":120,"mode":0,"inputs":[{"localized_name":"images","name":"images","type":"IMAGE","link":408},{"localized_name":"audio","name":"audio","shape":7,"type":"AUDIO","link":null},{"localized_name":"fps","name":"fps","type":"FLOAT","widget":{"name":"fps"},"link":406}],"outputs":[{"localized_name":"VIDEO","name":"VIDEO","type":"VIDEO","links":[410]}],"properties":{"cnr_id":"comfy-core","ver":"0.6.0","Node name for S&R":"CreateVideo"},"widgets_values":[30]},{"id":375,"type":"ImageScale","pos":[464.66149114943516,1256.03674290922],"size":[270,130],"flags":{},"order":66,"mode":0,"inputs":[{"localized_name":"image","name":"image","type":"IMAGE","link":400},{"localized_name":"upscale_method","name":"upscale_method","type":"COMBO","widget":{"name":"upscale_method"},"link":null},{"localized_name":"width","name":"width","type":"INT","widget":{"name":"width"},"link":null},{"localized_name":"height","name":"height","type":"INT","widget":{"name":"height"},"link":null},{"localized_name":"crop","name":"crop","type":"COMBO","widget":{"name":"crop"},"link":null}],"outputs":[{"localized_name":"IMAGE","name":"IMAGE","type":"IMAGE","links":[402]}],"properties":{"cnr_id":"comfy-core","ver":"0.12.3","Node name for S&R":"ImageScale"},"widgets_values":["nearest-exact",720,1280,"disabled"]},{"id":75,"type":"ImageResizeKJ","pos":[800.4143976463384,1263.4844527319449],"size":[280.83333333333337,218],"flags":{},"order":80,"mode":0,"inputs":[{"localized_name":"image","name":"image","type":"IMAGE","link":402},{"localized_name":"get_image_size","name":"get_image_size","shape":7,"type":"IMAGE","link":null},{"localized_name":"width","name":"width","type":"INT","widget":{"name":"width"},"link":null},{"localized_name":"height","name":"height","type":"INT","widget":{"name":"height"},"link":null},{"localized_name":"upscale_method","name":"upscale_method","type":"COMBO","widget":{"name":"upscale_method"},"link":null},{"localized_name":"keep_proportion","name":"keep_proportion","type":"BOOLEAN","widget":{"name":"keep_proportion"},"link":null},{"localized_name":"divisible_by","name":"divisible_by","type":"INT","widget":{"name":"divisible_by"},"link":null},{"localized_name":"crop","name":"crop","shape":7,"type":"COMBO","widget":{"name":"crop"},"link":null}],"outputs":[{"localized_name":"IMAGE","name":"IMAGE","type":"IMAGE","slot_index":0,"links":[87,93,101]},{"localized_name":"width","name":"width","type":"INT","links":null},{"localized_name":"height","name":"height","type":"INT","links":null}],"properties":{"cnr_id":"comfyui-kjnodes","ver":"16a335c8c40b1b3eef8b770022276004d5bea66b","Node name for S&R":"ImageResizeKJ"},"widgets_values":[720,1280,"bilinear",true,2,0],"color":"#323","bgcolor":"#535"},{"id":380,"type":"SaveVideo","pos":[3686.436908144201,1928.2390703404947],"size":[270,578],"flags":{},"order":119,"mode":0,"inputs":[{"localized_name":"video","name":"video","type":"VIDEO","link":412},{"localized_name":"filename_prefix","name":"filename_prefix","type":"STRING","widget":{"name":"filename_prefix"},"link":null},{"localized_name":"format","name":"format","type":"COMBO","widget":{"name":"format"},"link":null},{"localized_name":"codec","name":"codec","type":"COMBO","widget":{"name":"codec"},"link":null}],"outputs":[],"properties":{"cnr_id":"comfy-core","ver":"0.7.0","Node name for S&R":"SaveVideo"},"widgets_values":["video/ComfyUI","auto","auto"]},{"id":354,"type":"LoadVideo","pos":[-202.3533718348269,3109.8083088650997],"size":[386.798828125,761.6423611111111],"flags":{},"order":35,"mode":0,"inputs":[{"localized_name":"file","name":"file","type":"COMBO","widget":{"name":"file"},"link":null},{"localized_name":"choose file to upload","name":"upload","type":"IMAGEUPLOAD","widget":{"name":"upload"},"link":null}],"outputs":[{"localized_name":"VIDEO","name":"VIDEO","type":"VIDEO","links":[376,393]}],"properties":{"cnr_id":"comfy-core","ver":"0.7.0","Node name for S&R":"LoadVideo"},"widgets_values":["ExperienceGuide_02.mp4","image"]},{"id":358,"type":"SaveVideo","pos":[3084.4759864229386,3272.953827312794],"size":[270,578],"flags":{},"order":115,"mode":0,"inputs":[{"localized_name":"video","name":"video","type":"VIDEO","link":383},{"localized_name":"filename_prefix","name":"filename_prefix","type":"STRING","widget":{"name":"filename_prefix"},"link":394},{"localized_name":"format","name":"format","type":"COMBO","widget":{"name":"format"},"link":null},{"localized_name":"codec","name":"codec","type":"COMBO","widget":{"name":"codec"},"link":null}],"outputs":[],"properties":{"cnr_id":"comfy-core","ver":"0.7.0","Node name for S&R":"SaveVideo"},"widgets_values":["video/ComfyUI","auto","auto"]},{"id":379,"type":"SaveVideo","pos":[3696.1429338447774,1285.1399412478988],"size":[270,578],"flags":{},"order":121,"mode":0,"inputs":[{"localized_name":"video","name":"video","type":"VIDEO","link":410},{"localized_name":"filename_prefix","name":"filename_prefix","type":"STRING","widget":{"name":"filename_prefix"},"link":411},{"localized_name":"format","name":"format","type":"COMBO","widget":{"name":"format"},"link":null},{"localized_name":"codec","name":"codec","type":"COMBO","widget":{"name":"codec"},"link":null}],"outputs":[],"properties":{"cnr_id":"comfy-core","ver":"0.7.0","Node name for S&R":"SaveVideo"},"widgets_values":["video/ComfyUI","auto","auto"]},{"id":374,"type":"LoadVideo","pos":[-184.76328928453833,1259.9267085721167],"size":[386.798828125,761.6423611111111],"flags":{},"order":36,"mode":0,"inputs":[{"localized_name":"file","name":"file","type":"COMBO","widget":{"name":"file"},"link":null},{"localized_name":"choose file to upload","name":"upload","type":"IMAGEUPLOAD","widget":{"name":"upload"},"link":null}],"outputs":[{"localized_name":"VIDEO","name":"VIDEO","type":"VIDEO","links":[399,404]}],"properties":{"cnr_id":"comfy-core","ver":"0.7.0","Node name for S&R":"LoadVideo"},"widgets_values":["Loop_Idle_TiltSmile.mp4","image"]},{"id":215,"type":"SaveVideo","pos":[5573.097642853065,-627.1362127345429],"size":[269.7916666666667,577.6296296296297],"flags":{},"order":77,"mode":0,"inputs":[{"localized_name":"video","name":"video","type":"VIDEO","link":226},{"localized_name":"filename_prefix","name":"filename_prefix","type":"STRING","widget":{"name":"filename_prefix"},"link":227},{"localized_name":"format","name":"format","type":"COMBO","widget":{"name":"format"},"link":null},{"localized_name":"codec","name":"codec","type":"COMBO","widget":{"name":"codec"},"link":null}],"outputs":[],"properties":{"cnr_id":"comfy-core","ver":"0.3.68","Node name for S&R":"SaveVideo"},"widgets_values":["video/A_720p_SeedVR2_128to1024","mp4","h264"],"shape":2},{"id":68,"type":"LoadVideo","pos":[2342.515013136387,-632.3447269913947],"size":[273.8541666666667,658.2222222222222],"flags":{},"order":37,"mode":0,"inputs":[{"localized_name":"file","name":"file","type":"COMBO","widget":{"name":"file"},"link":null},{"localized_name":"choose file to upload","name":"upload","type":"IMAGEUPLOAD","widget":{"name":"upload"},"link":null}],"outputs":[{"localized_name":"VIDEO","name":"VIDEO","type":"VIDEO","links":[235,282]}],"properties":{"cnr_id":"comfy-core","ver":"0.3.68","Node name for S&R":"LoadVideo"},"widgets_values":["ExperienceGuide_01_Hongdae.mp4","image"]}],"links":[[80,67,0,66,0,"VIDEO"],[81,63,0,67,0,"IMAGE"],[86,73,0,71,0,"IMAGE"],[87,75,0,72,0,"IMAGE"],[88,79,1,73,0,"MASK"],[89,78,1,74,0,"MASK"],[93,75,0,78,0,"IMAGE"],[94,79,1,78,1,"MASK"],[95,81,0,79,0,"SAM_MODEL"],[96,80,0,79,1,"GROUNDING_DINO_MODEL"],[97,72,0,79,2,"IMAGE"],[101,75,0,87,0,"IMAGE"],[122,133,0,130,0,"IMAGE"],[161,132,0,162,0,"STRING"],[206,199,0,198,0,"STRING"],[207,196,0,199,0,"STRING"],[212,199,0,66,1,"STRING"],[215,61,0,206,0,"IMAGE"],[216,206,0,62,0,"IMAGE"],[217,212,0,207,0,"STRING"],[218,211,0,210,0,"IMAGE"],[224,214,0,212,0,"STRING"],[226,210,0,215,0,"VIDEO"],[227,212,0,215,1,"STRING"],[235,68,0,209,0,"VIDEO"],[242,221,0,222,0,"VIDEO"],[243,222,0,223,0,"IMAGE"],[245,222,0,224,0,"IMAGE"],[246,224,0,225,0,"IMAGE"],[247,225,0,133,0,"IMAGE"],[248,223,0,133,1,"IMAGE"],[249,222,2,226,2,"FLOAT"],[250,130,0,226,0,"IMAGE"],[251,226,0,227,0,"VIDEO"],[259,209,0,236,0,"IMAGE"],[260,209,1,237,0,"AUDIO"],[261,209,2,238,0,"FLOAT"],[262,239,0,211,0,"IMAGE"],[263,208,0,240,0,"SEEDVR2_DIT"],[264,219,0,241,0,"SEEDVR2_VAE"],[265,242,0,211,1,"SEEDVR2_DIT"],[266,243,0,211,2,"SEEDVR2_VAE"],[268,246,0,63,1,"SEEDVR2_DIT"],[271,247,0,61,0,"IMAGE"],[272,248,0,67,1,"AUDIO"],[273,249,0,67,2,"FLOAT"],[276,252,0,199,1,"STRING"],[277,61,0,63,0,"IMAGE"],[278,253,0,210,1,"AUDIO"],[279,254,0,210,2,"FLOAT"],[280,255,0,212,1,"STRING"],[281,244,0,63,2,"SEEDVR2_VAE"],[282,68,0,261,0,"VIDEO"],[284,261,0,263,0,"STRING"],[287,267,0,265,0,"STRING"],[288,263,0,265,1,"STRING"],[289,265,0,250,0,"STRING"],[291,265,0,271,0,"STRING"],[292,263,0,272,0,"STRING"],[294,222,2,274,0,"FLOAT"],[295,274,0,130,4,"INT"],[296,279,0,276,0,"STRING"],[297,277,0,278,0,"STRING"],[298,275,0,279,0,"STRING"],[300,279,0,280,0,"STRING"],[302,221,0,277,0,"VIDEO"],[303,278,0,282,0,"STRING"],[307,284,0,162,1,"STRING"],[308,162,0,164,0,"STRING"],[309,162,0,227,1,"STRING"],[332,282,0,308,0,"STRING"],[333,308,0,279,1,"STRING"],[343,323,3,325,0,"VHS_VIDEOINFO"],[348,330,0,329,0,"STRING"],[350,331,0,332,0,"STRING"],[351,329,0,332,1,"STRING"],[352,332,0,333,0,"STRING"],[354,327,0,330,0,"STRING"],[355,334,0,335,0,"STRING"],[357,335,0,336,0,"STRING"],[358,332,0,335,1,"STRING"],[370,225,0,345,0,"IMAGE"],[371,357,0,348,0,"MASK"],[372,348,0,349,0,"IMAGE"],[373,353,2,349,2,"FLOAT"],[374,356,0,351,0,"MASK"],[375,355,0,352,0,"VIDEO"],[376,354,0,353,0,"VIDEO"],[377,351,0,355,0,"IMAGE"],[378,353,2,355,2,"FLOAT"],[380,350,0,357,0,"VIDEOMAMA_PIPELINE"],[382,356,0,357,2,"MASK"],[383,349,0,358,0,"VIDEO"],[385,367,0,362,0,"STRING"],[386,364,0,363,0,"STRING"],[387,366,0,363,1,"STRING"],[388,362,0,366,0,"STRING"],[389,370,0,368,0,"STRING"],[390,363,0,369,0,"STRING"],[391,365,0,370,0,"STRING"],[392,363,0,370,1,"STRING"],[393,354,0,367,0,"VIDEO"],[394,370,0,358,1,"STRING"],[396,353,0,372,0,"IMAGE"],[397,372,0,356,0,"IMAGE"],[398,372,0,357,1,"IMAGE"],[399,374,0,373,0,"VIDEO"],[400,373,0,375,0,"IMAGE"],[402,375,0,75,0,"IMAGE"],[403,373,2,339,0,"FLOAT"],[404,374,0,327,0,"VIDEO"],[405,340,0,377,2,"FLOAT"],[406,378,0,376,2,"FLOAT"],[407,78,0,377,0,"IMAGE"],[408,74,0,376,0,"IMAGE"],[410,376,0,379,0,"VIDEO"],[411,335,0,379,1,"STRING"],[412,377,0,380,0,"VIDEO"]],"groups":[{"id":1,"title":"Upscale Main Workflow - SeedVR2","bounding":[2261.01083179085,-861.0777456411456,3656.619903297763,1344.6900687632171],"color":"#3f789e","font_size":24,"flags":{}},{"id":2,"title":"Video Mask Workflow - MatAnyone Video Kytra","bounding":[-222.60479616318253,1166.9026909859983,1774.5534887739477,875.4935773651449],"color":"#3f789e","font_size":24,"flags":{}},{"id":3,"title":"Process Video Matting","bounding":[1597.3230796610383,1174.7701216959579,1046.5305280554426,868.6252058635692],"color":"#3f789e","font_size":24,"flags":{}},{"id":4,"title":"Video Combine Results","bounding":[2670.522623645171,1178.611999830602,1678.772956488424,853.2392067469898],"color":"#3f789e","font_size":24,"flags":{}},{"id":5,"title":"Morph Workflow - Video End Frame to Start Frame","bounding":[-294.46623991138836,-858.7744857001527,2523.5832526268214,1171.486873582893],"color":"#3f789e","font_size":24,"flags":{}},{"id":6,"title":"Naming","bounding":[889.9029736427699,2060.055931758903,2041.268948134932,480.0365640474147],"color":"#3f789e","font_size":24,"flags":{}},{"id":7,"title":"Upscale Main Workflow - SeedVR2 Face Only (Deprecated)","bounding":[6105.128657321896,-851.6637827230633,2567.046121508288,786.814365497017],"color":"#3f789e","font_size":24,"flags":{}},{"id":8,"title":"Naming","bounding":[627.1843235599969,-835.5425647539903,354.42570287188425,143.03828365989625],"color":"#3f789e","font_size":24,"flags":{}},{"id":9,"title":"Video Mask Workflow - VideoMaMa","bounding":[-259.73964123482017,2772.289854703768,3693.7604637481254,1168.0520830329979],"color":"#3f789e","font_size":24,"flags":{}},{"id":10,"title":"Naming","bounding":[848.2957388770233,4026.1388792445114,2041.268948134932,480.0365640474147],"color":"#3f789e","font_size":24,"flags":{}}],"config":{},"extra":{"ds":{"scale":1.0834705943388425,"offset":[-1322.1849044988599,1126.7453334261202]},"workflowRendererVersion":"LG"},"version":0.4}